{
  "checks": {
    "browser_only": true,
    "no_python_runtime_required": true,
    "no_backend_required": true,
    "relationship_labels_enforced": {
      "jasper": "Momma",
      "william": "Papa"
    },
    "unique_response_counts_per_bank": {
      "william": {
        "mental_health": 1000,
        "emotional_health": 1000,
        "physical_health": 1000,
        "dbt_help": 1000,
        "life_impact": 1000,
        "tasks": 1000,
        "store": 1000
      },
      "jasper": {
        "mental_health": 1000,
        "emotional_health": 1000,
        "physical_health": 1000,
        "dbt_help": 1000,
        "life_impact": 1000,
        "tasks": 1000,
        "store": 1000
      }
    },
    "total_generated_responses": 14000,
    "source_json_preserved_under_json_source": true,
    "inline_data_bundle_for_file_mode": true
  },
  "notes": "Generated by deterministic Python build script; runtime is HTML/CSS/JS/JSON only."
}